{"is_source_file": false, "format": null, "description": null, "external_files": [], "external_methods": [], "published": [], "classes": [], "methods": [], "calls": [], "search-terms": ["layout", "XML", "LinearLayout", "RecyclerView", "fragment_categories", "app", "android"], "state": 2, "file_id": 24, "knowledge_revision": 121, "git_revision": "", "hash": "3de514ed257586adc027075efd0fb853", "format-version": 4, "code-base-name": "notes_frontend", "filename": "notes_frontend/app/src/main/res/layout/fragment_categories.xml", "revision_history": [{"121": ""}]}